README
setup.py
django_stdfile.egg-info/PKG-INFO
django_stdfile.egg-info/SOURCES.txt
django_stdfile.egg-info/dependency_links.txt
django_stdfile.egg-info/top_level.txt
stdfile/__init__.py
stdfile/db/__init__.py
stdfile/db/fields.py
stdfile/forms/__init__.py
stdfile/forms/fields.py
stdfile/forms/widgets.py