Metadata-Version: 1.0
Name: django-stdfile
Version: 0.5
Summary: Django application that improves management of FileFields
Home-page: https://tracpub.yaco.es/djangoapps/wiki/StdFile
Author: Yaco Sistemas S.L.
Author-email: pmartin@yaco.es
License: LGPL 3
Keywords: django stdfiles filefields files
Platform: UNKNOWN
Classifier: Development Status :: 4 - Beta
Classifier: Framework :: Django
Classifier: License :: OSI Approved :: GNU Library or Lesser General Public License (LGPL)
